esporifai/__init__.py
esporifai/__main__.py
esporifai/api.py
esporifai/cli.py
esporifai/constants.py
esporifai/utils.py
esporifai-0.2.2.dist-info/LICENSE
esporifai-0.2.2.dist-info/METADATA
esporifai-0.2.2.dist-info/WHEEL
esporifai-0.2.2.dist-info/entry_points.txt
esporifai-0.2.2.dist-info/top_level.txt
esporifai-0.2.2.dist-info/RECORD
