Metadata-Version: 2.1
Name: esporifai
Version: 0.2.2
Summary: A simple CLI to get data from the Spotify API
Home-page: https://github.com/chekos/esporifai
Author: Sergio Sánchez Zavala
License: Apache License, Version 2.0
Project-URL: Issues, https://github.com/chekos/esporifai/issues
Project-URL: CI, https://github.com/chekos/esporifai/actions
Project-URL: Changelog, https://github.com/chekos/esporifai/releases
Requires-Python: >=3.7
License-File: LICENSE
Requires-Dist: httpx ==0.23.0
Requires-Dist: playwright ==1.24.1
Requires-Dist: python-dotenv ==0.20.0
Requires-Dist: pytz ==2022.1
Requires-Dist: rich ==12.5.1
Requires-Dist: typer ==0.6.1
Provides-Extra: dev
Requires-Dist: black >=22.1.0 ; extra == 'dev'
Requires-Dist: datasette >=0.60.2 ; extra == 'dev'
Requires-Dist: ipykernel >=6.9.1 ; extra == 'dev'
Requires-Dist: isort >=5.10.1 ; extra == 'dev'
Requires-Dist: pytest >=7.0.1 ; extra == 'dev'
Requires-Dist: pytest-dotenv >=0.5.2 ; extra == 'dev'
Requires-Dist: ipywidgets ==7.6.5 ; extra == 'dev'
Provides-Extra: jupyter
Requires-Dist: ipywidgets ==7.6.5 ; extra == 'jupyter'
Provides-Extra: test
Requires-Dist: pytest >=7.0.1 ; extra == 'test'
Requires-Dist: pytest-dotenv >=0.5.2 ; extra == 'test'
